Workbook

Sheet Paramètres
A1: MÉTRÉ — Paramètres modifiables (en bleu)
A3: Hauteur sous plafond (m) | B3: 2.5
A4: Nb de couches de peinture | B4: 2
A5: Rendement peinture (m²/L) | B5: 10
A6: Marge de perte peinture | B6: 0.1
A7: Marge de perte carrelage | B7: 0.1
A8: Marge de perte placo | B8: 0.1
A10: PRIX UNITAIRES (€)
A11: Prix peinture (€/L) | B11: 4.5
A12: Prix carrelage (€/m²) | B12: 25
A13: Prix placo (€/m²) | B13: 12
A14: Prix plinthe (€/ml) | B14: 6
A15: TVA | B15: 0.2

Sheet Métré par pièce
A1: MÉTRÉ PAR PIÈCE — surfaces, plinthes, murs
A3: Pièce | B3: Surface sol (m²) | C3: HSP (m) | D3: Périmètre estimé (ml) | E3: Surface murs brute (m²) | F3: Ouvertures (m²) | G3: Surface murs nette (m²)
A4: Cuisine | B4: 13 | C4: =Paramètres!$B$3 -> 2.5 | D4: =ROUND(4*SQRT(B4),1) -> 14.4 | E4: =ROUND(D4*C4,1) -> 36 | F4: 3 | G4: =ROUND(E4-F4,1) -> 33
A5: Séjour | B5: 19 | C5: =Paramètres!$B$3 -> 2.5 | D5: =ROUND(4*SQRT(B5),1) -> 17.4 | E5: =ROUND(D5*C5,1) -> 43.5 | F5: 5 | G5: =ROUND(E5-F5,1) -> 38.5
A6: Salle d'eau | B6: 8 | C6: =Paramètres!$B$3 -> 2.5 | D6: =ROUND(4*SQRT(B6),1) -> 11.3 | E6: =ROUND(D6*C6,1) -> 28.3 | F6: 1.6 | G6: =ROUND(E6-F6,1) -> 26.7
A7: WC | B7: 2 | C7: =Paramètres!$B$3 -> 2.5 | D7: =ROUND(4*SQRT(B7),1) -> 5.7 | E7: =ROUND(D7*C7,1) -> 14.3 | F7: 1.6 | G7: =ROUND(E7-F7,1) -> 12.7
A8: Chambre 1 | B8: 12 | C8: =Paramètres!$B$3 -> 2.5 | D8: =ROUND(4*SQRT(B8),1) -> 13.9 | E8: =ROUND(D8*C8,1) -> 34.8 | F8: 3.1 | G8: =ROUND(E8-F8,1) -> 31.7
A9: Chambre 2 | B9: 10 | C9: =Paramètres!$B$3 -> 2.5 | D9: =ROUND(4*SQRT(B9),1) -> 12.6 | E9: =ROUND(D9*C9,1) -> 31.5 | F9: 3.1 | G9: =ROUND(E9-F9,1) -> 28.4
A10: Chambre 3 | B10: 9 | C10: =Paramètres!$B$3 -> 2.5 | D10: =ROUND(4*SQRT(B10),1) -> 12 | E10: =ROUND(D10*C10,1) -> 30 | F10: 3.1 | G10: =ROUND(E10-F10,1) -> 26.9
A11: Couloir | B11: 7 | C11: =Paramètres!$B$3 -> 2.5 | D11: =ROUND(4*SQRT(B11),1) -> 10.6 | E11: =ROUND(D11*C11,1) -> 26.5 | F11: 3.2 | G11: =ROUND(E11-F11,1) -> 23.3
A12: Galerie | B12: 5 | C12: =Paramètres!$B$3 -> 2.5 | D12: =ROUND(4*SQRT(B12),1) -> 8.9 | E12: =ROUND(D12*C12,1) -> 22.3 | F12: 1.6 | G12: =ROUND(E12-F12,1) -> 20.7
A13: TOTAL | B13: =SUM(B4:B12) -> 85 | D13: =SUM(D4:D12) -> 106.8 | E13: =SUM(E4:E12) -> 267.2 | F13: =SUM(F4:F12) -> 25.3 | G13: =SUM(G4:G12) -> 241.9

Sheet Matériaux & quantités
A1: MATÉRIAUX & QUANTITÉS
A3: Matériau | B3: Quantité | C3: Unité
A4: Peinture murs | B4: =ROUND('Métré par pièce'!$G$13*Paramètres!$B$4/Paramètres!$B$5*(1+Paramètres!$B$6),1) -> 53.2 | C4: L
A5: Carrelage sol | B5: =ROUND('Métré par pièce'!$B$13*(1+Paramètres!$B$7),1) -> 93.5 | C5: m²
A6: Placo plafond | B6: =ROUND('Métré par pièce'!$B$13*(1+Paramètres!$B$8),1) -> 93.5 | C6: m²
A7: Plinthes | B7: =ROUND('Métré par pièce'!$D$13*0.9,1) -> 96.1 | C7: ml

Sheet Récap budget
A1: RÉCAP BUDGET (estimation)
A3: Poste | B3: Quantité | C3: Prix unitaire (€) | D3: Coût (€)
A4: Peinture | B4: ='Matériaux & quantités'!B4 -> 53.2 | C4: =Paramètres!$B$11 -> 4.5 | D4: =ROUND(B4*C4,0) -> 239
A5: Carrelage | B5: ='Matériaux & quantités'!B5 -> 93.5 | C5: =Paramètres!$B$12 -> 25 | D5: =ROUND(B5*C5,0) -> 2338
A6: Placo | B6: ='Matériaux & quantités'!B6 -> 93.5 | C6: =Paramètres!$B$13 -> 12 | D6: =ROUND(B6*C6,0) -> 1122
A7: Plinthes | B7: ='Matériaux & quantités'!B7 -> 96.1 | C7: =Paramètres!$B$14 -> 6 | D7: =ROUND(B7*C7,0) -> 577
A8: TOTAL HT | D8: =SUM(D4:D7) -> 4276
A9: TVA | D9: =ROUND(D8*Paramètres!$B$15,0) -> 855
A10: TOTAL TTC | D10: =D8+D9 -> 5131
